<?xml version="1.0" encoding="UTF-8"?>
<jsdl:JobDefinition xmlns="http://www.example.org/"
	xmlns:jsdl="http://schemas.ggf.org/jsdl/2005/11/jsdl"
	xmlns:jsdl-posix="http://schemas.ggf.org/jsdl/2005/11/jsdl-posix"
	xmlns:xsi="http://www.w3.org/2001/XMLSchema-instance">
	
	<jsdl:JobDescription>
		<jsdl:JobIdentification>
			<jsdl:JobName>HelloWorld</jsdl:JobName>
			<jsdl:Description>A simple, example invocation to run a batch
			file in Windows that prints out Hello World and save it
			in the local directory as helloworld.txt
			</jsdl:Description>
		</jsdl:JobIdentification>
		
		<jsdl:Application>
			<jsdl:ApplicationName>helloworld</jsdl:ApplicationName>
			<jsdl-posix:POSIXApplication>
				<jsdl-posix:Executable>
					helloworld.bat
				</jsdl-posix:Executable>
				<jsdl-posix:Output>stdout</jsdl-posix:Output>				
			</jsdl-posix:POSIXApplication>
		</jsdl:Application>

		<jsdl:DataStaging>
			<jsdl:FileName>helloworld.bat</jsdl:FileName>
			<jsdl:CreationFlag>overwrite</jsdl:CreationFlag>
			<jsdl:DeleteOnTermination>true</jsdl:DeleteOnTermination>
			<jsdl:Source>
				<jsdl:URI>http://www.cs.virginia.edu/~cbs6n/survey/helloworld.bat</jsdl:URI>
			</jsdl:Source>
		</jsdl:DataStaging>
		
		<jsdl:DataStaging>
			<jsdl:FileName>stdout</jsdl:FileName>
			<jsdl:CreationFlag>overwrite</jsdl:CreationFlag>
			<jsdl:DeleteOnTermination>true</jsdl:DeleteOnTermination>
			<jsdl:Target>
				<jsdl:URI>rns:helloworld.txt</jsdl:URI>
			</jsdl:Target>
		</jsdl:DataStaging>
	</jsdl:JobDescription>
	
</jsdl:JobDefinition>
